tree_hugger/__init__.py
tree_hugger/exceptions.py
tree_hugger/setup_logging.py
tree_hugger/cli/__init__.py
tree_hugger/cli/create_libs.py
tree_hugger/cli/download_libs.py
tree_hugger/cli/os_detector.py
tree_hugger/core/__init__.py
tree_hugger/core/code_parser.py
tree_hugger/core/queries.py
tree_hugger/core/parser/__init__.py
tree_hugger/core/parser/cpp/__init__.py
tree_hugger/core/parser/cpp/cpp_parser.py
tree_hugger/core/parser/cpp/queries.yml
tree_hugger/core/parser/java/__init__.py
tree_hugger/core/parser/java/java_parser.py
tree_hugger/core/parser/java/queries.yml
tree_hugger/core/parser/javascript/__init__.py
tree_hugger/core/parser/javascript/javascript_parser.py
tree_hugger/core/parser/javascript/queries.yml
tree_hugger/core/parser/php/__init__.py
tree_hugger/core/parser/php/php_parser.py
tree_hugger/core/parser/php/queries.yml
tree_hugger/core/parser/python/__init__.py
tree_hugger/core/parser/python/python_parser.py
tree_hugger/core/parser/python/queries.yml
tree_hugger-0.10.1.dist-info/LICENSE
tree_hugger-0.10.1.dist-info/METADATA
tree_hugger-0.10.1.dist-info/WHEEL
tree_hugger-0.10.1.dist-info/entry_points.txt
tree_hugger-0.10.1.dist-info/top_level.txt
tree_hugger-0.10.1.dist-info/RECORD
