Metadata-Version: 2.1
Name: tree-hugger
Version: 0.10.1
Summary: A light-weight, Extendable, high level, universal code parser built on top of tree-sitter
Home-page: https://github.com/autosoft-dev/tree-hugger
Author: CodistAI
Author-email: shubhadeep@cdist-ai.com
License: MIT
Platform: UNKNOWN
Classifier: License :: OSI Approved :: MIT License
Classifier: Programming Language :: Python :: 3
Classifier: Programming Language :: Python :: 3.6
Requires-Dist: tree-sitter
Requires-Dist: pygit2
Requires-Dist: pytest
Requires-Dist: PyYAML
